{"version": 0.6, "generator": "Overpass API 0.7.62.10 2d4cfc48", "osm3s": {"timestamp_osm_base": "2026-02-03T09:51:15Z", "copyright": "The data included in this document is from www.openstreetmap.org. The data is made available under ODbL."}, "elements": [{"type": "node", "id": 338289697, "lat": 50.8473727, "lon": 4.2908173}, {"type": "node", "id": 416562772, "lat": 50.8463528, "lon": 4.2907563}, {"type": "node", "id": 416562773, "lat": 50.8462941, "lon": 4.2900559}, {"type": "node", "id": 416562774, "lat": 50.8463714, "lon": 4.2897888}, {"type": "node", "id": 416562775, "lat": 50.8469552, "lon": 4.2893165}, {"type": "node", "id": 416562776, "lat": 50.8474473, "lon": 4.2890162}, {"type": "node", "id": 416562777, "lat": 50.8477763, "lon": 4.29074}, {"type": "node", "id": 416562778, "lat": 50.847175, "lon": 4.2908552}, {"type": "node", "id": 416562779, "lat": 50.8472194, "lon": 4.2910255}, {"type": "node", "id": 416562921, "lat": 50.8480702, "lon": 4.2887286}, {"type": "node", "id": 416562922, "lat": 50.8481527, "lon": 4.2887072}, {"type": "node", "id": 416562923, "lat": 50.8483498, "lon": 4.288731}, {"type": "node", "id": 416562924, "lat": 50.8484406, "lon": 4.2890687}, {"type": "node", "id": 416562925, "lat": 50.848627, "lon": 4.290344}, {"type": "node", "id": 416562926, "lat": 50.8483049, "lon": 4.2905444}, {"type": "node", "id": 2320381070, "lat": 50.847604, "lon": 4.2897535}, {"type": "node", "id": 2320381071, "lat": 50.8480117, "lon": 4.2894771}, {"type": "node", "id": 2320384257, "lat": 50.848146, "lon": 4.2892995}, {"type": "node", "id": 2505793113, "lat": 50.8395743, "lon": 4.2927451}, {"type": "node", "id": 2505793132, "lat": 50.8395938, "lon": 4.2930865}, {"type": "node", "id": 2505793154, "lat": 50.8396224, "lon": 4.2932081}, {"type": "node", "id": 2505793167, "lat": 50.8396298, "lon": 4.2922646}, {"type": "node", "id": 2505793194, "lat": 50.8396455, "lon": 4.2921995, "tags": {"addr:housenumber": "231", "addr:street": "Rue Adolphe Willemyns - Adolphe Willemynsstraat", "entrance": "yes", "ref:UrbIS": "7720979"}}, {"type": "node", "id": 2505793195, "lat": 50.8396479, "lon": 4.2930574}, {"type": "node", "id": 2505793234, "lat": 50.8396641, "lon": 4.2921217}, {"type": "node", "id": 2505793261, "lat": 50.8396752, "lon": 4.2931762}, {"type": "node", "id": 2505793297, "lat": 50.8397015, "lon": 4.2932841}, {"type": "node", "id": 2505793356, "lat": 50.8397435, "lon": 4.2923274}, {"type": "node", "id": 2505793382, "lat": 50.8397743, "lon": 4.2933379}, {"type": "node", "id": 2505793384, "lat": 50.8397764, "lon": 4.2924699}, {"type": "node", "id": 2505793390, "lat": 50.8397819, "lon": 4.2933699}, {"type": "node", "id": 2505793399, "lat": 50.8397886, "lon": 4.2933985}, {"type": "node", "id": 2505793457, "lat": 50.8398059, "lon": 4.2921486}, {"type": "node", "id": 2505793674, "lat": 50.8399299, "lon": 4.2923801}, {"type": "node", "id": 2505793738, "lat": 50.8399508, "lon": 4.2933481}, {"type": "node", "id": 2505793812, "lat": 50.8399892, "lon": 4.2932766}, {"type": "node", "id": 2505793833, "lat": 50.8400005, "lon": 4.2933202}, {"type": "node", "id": 2505793847, "lat": 50.8400057, "lon": 4.2935884}, {"type": "node", "id": 2505793900, "lat": 50.84002, "lon": 4.2930873}, {"type": "node", "id": 2505793963, "lat": 50.8400527, "lon": 4.2929275}, {"type": "node", "id": 2505793972, "lat": 50.840055, "lon": 4.2932365}, {"type": "node", "id": 2505793975, "lat": 50.8400576, "lon": 4.2929247}, {"type": "node", "id": 2505793981, "lat": 50.8400609, "lon": 4.2930634}, {"type": "node", "id": 2505794110, "lat": 50.8402753, "lon": 4.2881305}, {"type": "node", "id": 2505794161, "lat": 50.8403403, "lon": 4.2881451}, {"type": "node", "id": 2505794162, "lat": 50.8403405, "lon": 4.288142}, {"type": "node", "id": 2505794171, "lat": 50.8403545, "lon": 4.2881476}, {"type": "node", "id": 2529068507, "lat": 50.8482666, "lon": 4.2902466}, {"type": "node", "id": 2529068508, "lat": 50.8482783, "lon": 4.2903468}, {"type": "node", "id": 2529068509, "lat": 50.8482914, "lon": 4.2904453}, {"type": "node", "id": 2529921842, "lat": 50.8468876, "lon": 4.291015}, {"type": "node", "id": 2529957378, "lat": 50.8468563, "lon": 4.2906459}, {"type": "node", "id": 2529957455, "lat": 50.8469264, "lon": 4.2910904}, {"type": "node", "id": 2529957744, "lat": 50.8477257, "lon": 4.2896834}, {"type": "node", "id": 2529957781, "lat": 50.8479792, "lon": 4.2895033}, {"type": "node", "id": 2529958062, "lat": 50.8480164, "lon": 4.2897902}, {"type": "node", "id": 2529958092, "lat": 50.848254, "lon": 4.2901446}, {"type": "node", "id": 2529958096, "lat": 50.8482988, "lon": 4.2905002}, {"type": "node", "id": 2587618724, "lat": 50.8410157, "lon": 4.2972008}, {"type": "node", "id": 2587618726, "lat": 50.8410163, "lon": 4.2972096}, {"type": "node", "id": 2587618728, "lat": 50.8410217, "lon": 4.2972085}, {"type": "node", "id": 2587618733, "lat": 50.841026, "lon": 4.2973157}, {"type": "node", "id": 2587618734, "lat": 50.8410269, "lon": 4.297327}, {"type": "node", "id": 2587618736, "lat": 50.8410314, "lon": 4.2973151}, {"type": "node", "id": 2587618737, "lat": 50.8410321, "lon": 4.2973262}, {"type": "node", "id": 2587618739, "lat": 50.8410368, "lon": 4.2974335}, {"type": "node", "id": 2587618740, "lat": 50.841038, "lon": 4.297444}, {"type": "node", "id": 2587618743, "lat": 50.8410425, "lon": 4.2974324}, {"type": "node", "id": 2587618744, "lat": 50.8410432, "lon": 4.2974431}, {"type": "node", "id": 2587618747, "lat": 50.8410477, "lon": 4.2975516}, {"type": "node", "id": 2587618748, "lat": 50.8410488, "lon": 4.2975613}, {"type": "node", "id": 2587618749, "lat": 50.8410536, "lon": 4.2975503}, {"type": "node", "id": 2587618750, "lat": 50.8410539, "lon": 4.29756}, {"type": "node", "id": 2587618751, "lat": 50.8410583, "lon": 4.2976686}, {"type": "node", "id": 2587618753, "lat": 50.8410593, "lon": 4.2976787}, {"type": "node", "id": 2587618754, "lat": 50.8410639, "lon": 4.2976673}, {"type": "node", "id": 2587618756, "lat": 50.8410644, "lon": 4.2976775}, {"type": "node", "id": 2587618762, "lat": 50.8410671, "lon": 4.2971887}, {"type": "node", "id": 2587618764, "lat": 50.8410692, "lon": 4.2977867}, {"type": "node", "id": 2587618768, "lat": 50.8410698, "lon": 4.2977952}, {"type": "node", "id": 2587618778, "lat": 50.8410732, "lon": 4.297764}, {"type": "node", "id": 2587618780, "lat": 50.8410752, "lon": 4.2977841}, {"type": "node", "id": 2587618784, "lat": 50.8410762, "lon": 4.2977938}, {"type": "node", "id": 2587618800, "lat": 50.8411239, "lon": 4.2971757}, {"type": "node", "id": 2587618806, "lat": 50.8411643, "lon": 4.2971667}, {"type": "node", "id": 2587618822, "lat": 50.8412087, "lon": 4.2977638}, {"type": "node", "id": 2587618828, "lat": 50.84122, "lon": 4.2971541}, {"type": "node", "id": 2587618832, "lat": 50.8412298, "lon": 4.297152}, {"type": "node", "id": 2587618844, "lat": 50.8412655, "lon": 4.2975439}, {"type": "node", "id": 2587618852, "lat": 50.8412782, "lon": 4.2976856}, {"type": "node", "id": 2587618854, "lat": 50.8412838, "lon": 4.2977468}, {"type": "node", "id": 2587618906, "lat": 50.8414787, "lon": 4.2974943}, {"type": "node", "id": 2587618917, "lat": 50.8414928, "lon": 4.2976367}, {"type": "node", "id": 2587618931, "lat": 50.8415486, "lon": 4.2976248}, {"type": "node", "id": 2587618935, "lat": 50.8415608, "lon": 4.2977531}, {"type": "node", "id": 2587618957, "lat": 50.8416396, "lon": 4.2969713}, {"type": "node", "id": 2587618967, "lat": 50.8416489, "lon": 4.2970823}, {"type": "node", "id": 2587618980, "lat": 50.8416552, "lon": 4.2969084}, {"type": "node", "id": 2587618982, "lat": 50.8416595, "lon": 4.2971956}, {"type": "node", "id": 2587618986, "lat": 50.8416655, "lon": 4.2970231}, {"type": "node", "id": 2587618988, "lat": 50.8416711, "lon": 4.2973096}, {"type": "node", "id": 2587618990, "lat": 50.8416755, "lon": 4.2971346}, {"type": "node", "id": 2587618992, "lat": 50.8416857, "lon": 4.2972473}, {"type": "node", "id": 2587618996, "lat": 50.8416961, "lon": 4.2973627}, {"type": "node", "id": 2587618998, "lat": 50.8417142, "lon": 4.2977178}, {"type": "node", "id": 2587619000, "lat": 50.8417217, "lon": 4.296892}, {"type": "node", "id": 2587619002, "lat": 50.8417611, "lon": 4.2973478}, {"type": "node", "id": 2587619004, "lat": 50.8417639, "lon": 4.297613}, {"type": "node", "id": 2587619006, "lat": 50.8417683, "lon": 4.2974256}, {"type": "node", "id": 2587619009, "lat": 50.8417689, "lon": 4.297432}, {"type": "node", "id": 2587619011, "lat": 50.8417723, "lon": 4.2977044}, {"type": "node", "id": 2587619013, "lat": 50.8417736, "lon": 4.2969955}, {"type": "node", "id": 2587619015, "lat": 50.8417852, "lon": 4.2974214}, {"type": "node", "id": 2587619017, "lat": 50.8417933, "lon": 4.297384}, {"type": "node", "id": 2587619019, "lat": 50.8418006, "lon": 4.29705}, {"type": "node", "id": 2587619021, "lat": 50.8418049, "lon": 4.2974166}, {"type": "node", "id": 2587619023, "lat": 50.8418055, "lon": 4.2974241}, {"type": "node", "id": 2587619025, "lat": 50.841811, "lon": 4.2971619}, {"type": "node", "id": 2587619028, "lat": 50.8418158, "lon": 4.2969861}, {"type": "node", "id": 2587619030, "lat": 50.8418188, "lon": 4.2975685}, {"type": "node", "id": 2587619033, "lat": 50.8418217, "lon": 4.2975997}, {"type": "node", "id": 2587619035, "lat": 50.8418254, "lon": 4.2971004}, {"type": "node", "id": 2587619037, "lat": 50.8418356, "lon": 4.2972138}, {"type": "node", "id": 4397853133, "lat": 50.8405944, "lon": 4.2872476}, {"type": "node", "id": 4397853134, "lat": 50.840595, "lon": 4.2875181}, {"type": "node", "id": 4397853143, "lat": 50.8407053, "lon": 4.2872461}, {"type": "node", "id": 4397853144, "lat": 50.8407053, "lon": 4.2875181}, {"type": "node", "id": 8647569923, "lat": 50.8400576, "lon": 4.2873635}, {"type": "node", "id": 8647569924, "lat": 50.8400594, "lon": 4.2874216}, {"type": "node", "id": 8647569925, "lat": 50.8400619, "lon": 4.2879996}, {"type": "node", "id": 8647569926, "lat": 50.8405989, "lon": 4.287189}, {"type": "node", "id": 8647569927, "lat": 50.8406133, "lon": 4.2871189}, {"type": "node", "id": 8647569928, "lat": 50.8406415, "lon": 4.2870394}, {"type": "node", "id": 8647569929, "lat": 50.8406622, "lon": 4.2869806}, {"type": "node", "id": 8647569930, "lat": 50.8406707, "lon": 4.2869224}, {"type": "node", "id": 8647569931, "lat": 50.8406559, "lon": 4.2868643}, {"type": "node", "id": 8647569932, "lat": 50.8406242, "lon": 4.2868175}, {"type": "node", "id": 8647569933, "lat": 50.8405795, "lon": 4.2867981}, {"type": "node", "id": 8647569934, "lat": 50.8405774, "lon": 4.2867306}, {"type": "node", "id": 8647569935, "lat": 50.8400263, "lon": 4.2867366}, {"type": "node", "id": 8647569936, "lat": 50.8400389, "lon": 4.2869151}, {"type": "node", "id": 8647569937, "lat": 50.8400676, "lon": 4.2869866}, {"type": "node", "id": 8647569938, "lat": 50.8400727, "lon": 4.287034}, {"type": "node", "id": 8647569939, "lat": 50.8400782, "lon": 4.2872398}, {"type": "node", "id": 8647569940, "lat": 50.8400571, "lon": 4.2873173}, {"type": "node", "id": 8647569941, "lat": 50.8406327, "lon": 4.2876421}, {"type": "node", "id": 8647569942, "lat": 50.8405998, "lon": 4.2881192}, {"type": "node", "id": 8647569943, "lat": 50.8400613, "lon": 4.2880912}, {"type": "node", "id": 8647569944, "lat": 50.8400651, "lon": 4.2875405}, {"type": "node", "id": 8647569945, "lat": 50.8400585, "lon": 4.2873901, "tags": {"entrance": "yes"}}, {"type": "node", "id": 11436007599, "lat": 50.8396533, "lon": 4.2921668, "tags": {"entrance": "yes"}}, {"type": "node", "id": 11436012040, "lat": 50.8400279, "lon": 4.2936211}, {"type": "node", "id": 11436012041, "lat": 50.8400192, "lon": 4.2935827}, {"type": "node", "id": 11436021447, "lat": 50.8396218, "lon": 4.2923046, "tags": {"barrier": "gate", "entrance": "yes"}}, {"type": "node", "id": 11436021448, "lat": 50.8395505, "lon": 4.2926005, "tags": {"barrier": "gate", "entrance": "yes"}}, {"type": "node", "id": 11436021451, "lat": 50.8395164, "lon": 4.2927391}, {"type": "node", "id": 11436021452, "lat": 50.8395718, "lon": 4.2925141}, {"type": "node", "id": 11436021453, "lat": 50.8396142, "lon": 4.2923425}, {"type": "node", "id": 11436055768, "lat": 50.8399469, "lon": 4.2916184}, {"type": "node", "id": 11436108609, "lat": 50.8397834, "lon": 4.2923391}, {"type": "node", "id": 11436108610, "lat": 50.8401253, "lon": 4.2932025}, {"type": "node", "id": 11436108611, "lat": 50.8401291, "lon": 4.2929401}, {"type": "node", "id": 11436108612, "lat": 50.8401341, "lon": 4.2925995}, {"type": "node", "id": 11436108613, "lat": 50.8401397, "lon": 4.2922115}, {"type": "node", "id": 11436108614, "lat": 50.840185, "lon": 4.2916451}, {"type": "node", "id": 11436108615, "lat": 50.8401478, "lon": 4.2916415}, {"type": "node", "id": 11436124469, "lat": 50.8399078, "lon": 4.2921679}, {"type": "node", "id": 11436137982, "lat": 50.8400168, "lon": 4.2935822}, {"type": "node", "id": 11436137983, "lat": 50.84006, "lon": 4.2936032}, {"type": "node", "id": 11436137984, "lat": 50.8401195, "lon": 4.2936331}, {"type": "node", "id": 11436137985, "lat": 50.8397568, "lon": 4.2932537}, {"type": "node", "id": 12290089509, "lat": 50.8477977, "lon": 4.2908614}, {"type": "node", "id": 12291866094, "lat": 50.8480826, "lon": 4.2894183}, {"type": "node", "id": 12291866095, "lat": 50.8480442, "lon": 4.2895876}, {"type": "node", "id": 12291866096, "lat": 50.8484732, "lon": 4.2892509}, {"type": "node", "id": 12291866097, "lat": 50.848202, "lon": 4.2897297}, {"type": "node", "id": 12291866098, "lat": 50.8482663, "lon": 4.2886883}, {"type": "node", "id": 12291866099, "lat": 50.8485094, "lon": 4.2894845}, {"type": "node", "id": 12291866100, "lat": 50.8485671, "lon": 4.2899053}, {"type": "node", "id": 12291963609, "lat": 50.8463243, "lon": 4.2899482}, {"type": "node", "id": 12291963610, "lat": 50.8463553, "lon": 4.289849}, {"type": "node", "id": 12291963611, "lat": 50.8464341, "lon": 4.2895324}, {"type": "node", "id": 12291963612, "lat": 50.8464244, "lon": 4.2895563}, {"type": "node", "id": 12291963613, "lat": 50.8464712, "lon": 4.2894917}, {"type": "node", "id": 12291963614, "lat": 50.8464589, "lon": 4.2895007}, {"type": "node", "id": 12291963615, "lat": 50.846445, "lon": 4.2895141}, {"type": "node", "id": 12291963616, "lat": 50.8464878, "lon": 4.2894853}, {"type": "node", "id": 12291963617, "lat": 50.8466878, "lon": 4.2894106}, {"type": "node", "id": 12291963618, "lat": 50.8467149, "lon": 4.289439}, {"type": "node", "id": 12291963619, "lat": 50.8474911, "lon": 4.2891079}, {"type": "node", "id": 12291963620, "lat": 50.8468934, "lon": 4.2910971}, {"type": "way", "id": 35552029, "nodes": [416562772, 416562773, 12291963609, 12291963610, 416562774, 12291963612, 12291963611, 12291963615, 12291963614, 12291963613, 12291963616, 12291963617, 12291963618, 416562775, 416562776, 12291963619, 2320381070, 416562777, 338289697, 416562778, 416562779, 2529957455, 12291963620, 2529921842, 2529957378, 416562772], "tags": {"amenity": "school", "contact:phone": "+32 2 521 78 01", "name": "Aux Sources du Gai Savoir"}}, {"type": "way", "id": 35552053, "nodes": [416562921, 416562922, 12291866098, 416562923, 416562924, 12291866096, 12291866099, 12291866100, 416562925, 416562926, 2529958096, 2529068509, 2529068508, 2529068507, 2529958092, 12291866097, 2529958062, 12291866095, 2320381071, 12291866094, 2320384257, 416562921], "tags": {"alt_name": "Sint Martinusinstituut", "amenity": "school", "contact:email": "directie@sint-martinuspaloke.be", "contact:mobile": "+32 492 29 79 68", "contact:website": "https://martinusleukeschool.be/", "name": "Sint Martinus"}}, {"type": "way", "id": 223101432, "nodes": [2320381071, 2529957781, 2529957744, 2320381070, 416562777, 12290089509, 416562926, 2529958096, 2529068509, 2529068508, 2529068507, 2529958092, 12291866097, 2529958062, 12291866095, 2320381071], "tags": {"amenity": "school", "contact:email": "sec.paloke@ind-groupe.be", "contact:phone": "+32 2 520 64 07", "name": "Institut Notre-Dame (Saint-Martin)", "school:language": "fr"}}, {"type": "way", "id": 252724059, "nodes": [2587619000, 2587619013, 2587619028, 2587619019, 2587619035, 2587619025, 2587619037, 2587619017, 2587619015, 2587619021, 2587619023, 2587619030, 2587619033, 2587619004, 2587619011, 2587618998, 2587618935, 2587618931, 2587618917, 2587618852, 2587618854, 2587618822, 2587618784, 2587618768, 2587618764, 2587618780, 2587618778, 2587618756, 2587618753, 2587618751, 2587618754, 2587618750, 2587618748, 2587618747, 2587618749, 2587618744, 2587618740, 2587618739, 2587618743, 2587618737, 2587618734, 2587618733, 2587618736, 2587618728, 2587618726, 2587618724, 2587618762, 2587618800, 2587618806, 2587618828, 2587618832, 2587618844, 2587618906, 2587619009, 2587619006, 2587619002, 2587618996, 2587618988, 2587618992, 2587618982, 2587618990, 2587618967, 2587618986, 2587618957, 2587618980, 2587619000], "tags": {"addr:housenumber": "170", "addr:street": "Rue du Potaerdenberg - Potaardenbergstraat", "amenity": "school", "building": "school", "name": "\u00c9cole fondamentale Claire Soleil P1-M18", "operator": "Commune d'Anderlecht - Gemeente Anderlecht", "operator:type": "public", "ref:UrbIS": "8003689"}}, {"type": "way", "id": 932885832, "nodes": [8647569941, 4397853134, 4397853144, 4397853143, 4397853133, 8647569926, 8647569927, 8647569928, 8647569929, 8647569930, 8647569931, 8647569932, 8647569933, 8647569934, 8647569935, 8647569936, 8647569937, 8647569938, 8647569939, 8647569940, 8647569923, 8647569945, 8647569924, 8647569944, 8647569925, 8647569943, 2505794110, 2505794162, 2505794161, 2505794171, 8647569942, 8647569941], "tags": {"addr:housenumber": "337", "addr:street": "Rue Adolphe Willemyns - Adolphe Willemynsstraat", "amenity": "school", "name": "\u00c9cole fondamentale Moortebeek"}}, {"type": "way", "id": 1232809132, "nodes": [2505793356, 2505793167, 2505793194, 11436007599, 2505793234, 2505793457, 11436124469, 11436055768, 11436108615, 11436108614, 11436108613, 11436108612, 11436108611, 11436108610, 2505793972, 2505793900, 2505793981, 2505793963, 2505793975, 2505793674, 2505793384, 11436108609, 2505793356], "tags": {"amenity": "school", "contact:email": "Sec.willemijns@ind-groupe.be", "contact:phone": "+32 2 522 95 90", "contact:website": "https://sites.google.com/indwillemijns.org/indwillemijns/", "name": "Institut Notre Dame Willemijns", "religion": "christian", "school:language": "fr"}}, {"type": "way", "id": 1232809963, "nodes": [2505793356, 2505793167, 11436021447, 11436021453, 11436021452, 11436021448, 11436021451, 2505793113, 2505793195, 2505793132, 2505793154, 2505793261, 2505793297, 11436137985, 2505793382, 2505793390, 2505793399, 2505793812, 2505793833, 2505793738, 2505793847, 11436137982, 11436012041, 11436012040, 11436137983, 11436137984, 11436108610, 2505793972, 2505793900, 2505793981, 2505793963, 2505793975, 2505793674, 2505793384, 11436108609, 2505793356], "tags": {"amenity": "school", "contact:email": "regina.assumptaschool@gmail.com", "contact:phone": "+32 2 522 66 59", "contact:website": "https://regina-assumpta.be/", "name": "Regina Assumpta Anderlecht", "school": "primary", "school:language": "nl", "short_name": "RAS"}}]}