{"version": 0.6, "generator": "Overpass API 0.7.62.10 2d4cfc48", "osm3s": {"timestamp_osm_base": "2026-02-03T09:05:09Z", "copyright": "The data included in this document is from www.openstreetmap.org. The data is made available under ODbL."}, "elements": [{"type": "node", "id": 766889457, "lat": 50.8575327, "lon": 4.3845223, "tags": {"amenity": "cafe", "name": "Rings"}}, {"type": "node", "id": 2357298752, "lat": 50.8541012, "lon": 4.3883967, "tags": {"amenity": "cafe", "name": "L'Orchid\u00e9e", "outdoor_seating": "yes"}}, {"type": "node", "id": 2357318252, "lat": 50.8526543, "lon": 4.3951171, "tags": {"amenity": "cafe", "cuisine": "french;omelette;soup", "internet_access": "wlan", "internet_access:fee": "no", "internet_access:ssid": "telnet-77D215C", "name": "Le Cadre Noir", "outdoor_seating": "yes"}}, {"type": "node", "id": 2357424660, "lat": 50.8528807, "lon": 4.3882327, "tags": {"amenity": "cafe", "contact:facebook": "lepetitcancale", "contact:mobile": "+32 488 08 21 64", "name": "Le P'tit Cancale"}}, {"type": "node", "id": 2403700024, "lat": 50.8491532, "lon": 4.3894539, "tags": {"amenity": "cafe", "name": "Friends", "outdoor_seating": "yes"}}, {"type": "node", "id": 7925665125, "lat": 50.8566783, "lon": 4.3895021, "tags": {"amenity": "cafe", "check_date": "2025-09-24", "contact:instagram": "https://www.instagram.com/arome1030/", "cuisine": "coffee_shop;bakery", "name": "Ar\u00f4me", "opening_hours": "Tu-Fr 07:00-18:00; Sa,Su 08:00-17:00", "outdoor_seating": "no"}}, {"type": "node", "id": 9983244667, "lat": 50.8559226, "lon": 4.3945154, "tags": {"amenity": "cafe", "check_date": "2022-08-28", "name": "Caffe Questo 1898"}}, {"type": "node", "id": 11513913816, "lat": 50.8520625, "lon": 4.3859989, "tags": {"amenity": "cafe", "name": "La Pub"}}, {"type": "node", "id": 11513913833, "lat": 50.8521347, "lon": 4.3862891, "tags": {"amenity": "cafe", "name": "Chez Pepe"}}]}