{"version": 0.6, "generator": "Overpass API 0.7.62.10 2d4cfc48", "osm3s": {"timestamp_osm_base": "2026-02-02T19:06:45Z", "copyright": "The data included in this document is from www.openstreetmap.org. The data is made available under ODbL."}, "elements": [{"type": "node", "id": 234693119, "lat": 50.8244211, "lon": 4.335998, "tags": {"name": "Rochefort", "public_transport": "stop_position", "railway": "tram_stop", "tram": "yes"}}, {"type": "node", "id": 234693191, "lat": 50.8207678, "lon": 4.3257891, "tags": {"name": "Union", "public_transport": "stop_position", "railway": "tram_stop", "tram": "yes"}}, {"type": "node", "id": 3115600526, "lat": 50.8235812, "lon": 4.3260768, "tags": {"name": "Wiels", "public_transport": "stop_position", "railway": "tram_stop", "tram": "yes"}}, {"type": "node", "id": 3115600755, "lat": 50.8242342, "lon": 4.3299696, "tags": {"name": "Berthelot", "public_transport": "stop_position", "railway": "tram_stop", "tram": "yes"}}, {"type": "node", "id": 3115600813, "lat": 50.8243508, "lon": 4.3354974, "tags": {"name": "Rochefort", "public_transport": "stop_position", "railway": "tram_stop", "tram": "yes"}}, {"type": "node", "id": 3141592622, "lat": 50.8241835, "lon": 4.3274464, "tags": {"name": "Wiels", "public_transport": "stop_position", "railway": "tram_stop", "tram": "yes"}}, {"type": "node", "id": 3141593461, "lat": 50.824881, "lon": 4.326311, "tags": {"name": "Wiels", "public_transport": "stop_position", "railway": "tram_stop", "tram": "yes"}}, {"type": "node", "id": 3141593501, "lat": 50.8269205, "lon": 4.3271562, "tags": {"name": "Orban", "public_transport": "stop_position", "railway": "tram_stop", "tram": "yes"}}, {"type": "node", "id": 3141593509, "lat": 50.8272678, "lon": 4.3274751, "tags": {"name": "Orban", "public_transport": "stop_position", "railway": "tram_stop", "tram": "yes"}}, {"type": "node", "id": 3141593561, "lat": 50.8289255, "lon": 4.3292491, "tags": {"name": "Imprimerie - Drukkerij", "name:fr": "Imprimerie", "name:nl": "Drukkerij", "public_transport": "stop_position", "railway": "tram_stop", "tram": "yes"}}, {"type": "node", "id": 3141593623, "lat": 50.8300226, "lon": 4.3307019, "tags": {"name": "Imprimerie - Drukkerij", "name:fr": "Imprimerie", "name:nl": "Drukkerij", "public_transport": "stop_position", "railway": "tram_stop", "tram": "yes"}}, {"type": "node", "id": 3141593692, "lat": 50.8313366, "lon": 4.3323216, "tags": {"name": "Avenue du Roi - Koningslaan", "name:fr": "Avenue du Roi", "name:nl": "Koningslaan", "public_transport": "stop_position", "railway": "tram_stop", "tram": "yes"}}, {"type": "node", "id": 3141593831, "lat": 50.8316585, "lon": 4.3327963, "tags": {"name": "Avenue du Roi - Koningslaan", "name:fr": "Avenue du Roi", "name:nl": "Koningslaan", "public_transport": "stop_position", "railway": "tram_stop", "tram": "yes"}}, {"type": "node", "id": 4594588105, "lat": 50.8314604, "lon": 4.3345078, "tags": {"name": "Avenue du Roi - Koningslaan", "name:fr": "Avenue du Roi", "name:nl": "Koningslaan", "public_transport": "stop_position", "railway": "tram_stop", "tram": "yes"}}, {"type": "node", "id": 5137643590, "lat": 50.8253137, "lon": 4.3386392, "tags": {"name": "Combaz", "public_transport": "stop_position", "railway": "tram_stop", "tram": "yes"}}, {"type": "node", "id": 5137679011, "lat": 50.8242203, "lon": 4.3311245, "tags": {"name": "Berthelot", "public_transport": "stop_position", "railway": "tram_stop", "tram": "yes"}}]}