{"version": 0.6, "generator": "Overpass API 0.7.62.10 2d4cfc48", "osm3s": {"timestamp_osm_base": "2026-02-03T09:29:45Z", "copyright": "The data included in this document is from www.openstreetmap.org. The data is made available under ODbL."}, "elements": [{"type": "node", "id": 66180313, "lat": 50.8601446, "lon": 4.3614901, "tags": {"internet_access": "wlan", "name": "Bruxelles-Nord - Brussel-Noord", "name:ar": "\u0628\u0631\u0648\u0643\u0633\u0644 \u0627\u0644\u0634\u0645\u0627\u0644\u064a\u0629", "name:de": "Br\u00fcssel-Nord", "name:en": "Brussels-North", "name:fr": "Bruxelles-Nord", "name:nl": "Brussel-Noord", "name:ur": "\u0628\u0631\u0633\u0644\u0632 \u0634\u0645\u0627\u0644", "network": "NMBS/SNCB", "network:wikidata": "Q524255", "operator": "NMBS/SNCB", "operator:wikidata": "Q524255", "public_transport": "station", "railway": "station", "railway:position:exact:L25": "0.076", "railway:position:exact:L27": "0.494", "railway:position:exact:L36": "0.494", "railway:position:exact:L36N": "0.530", "railway:position:exact:L50": "0.478", "railway:ref": "FBN", "ref:EU:PLC": "BE00221", "train": "yes", "uic_ref": "8812005", "website": "https://www.belgiantrain.be/station-information/brussel-bruxelles/noord-nord", "wheelchair": "limited", "wikidata": "Q660792", "wikipedia": "nl:Station Brussel-Noord", "zone:NMBS_SNCB": "Bruxelles - Brussel"}}]}