{"version": 0.6, "generator": "Overpass API 0.7.62.10 2d4cfc48", "osm3s": {"timestamp_osm_base": "2026-02-02T18:26:51Z", "copyright": "The data included in this document is from www.openstreetmap.org. The data is made available under ODbL."}, "elements": [{"type": "node", "id": 402728086, "lat": 50.8374377, "lon": 4.4320549, "tags": {"alt_name": "Le Wolu", "amenity": "bar", "name": "L'Aperitivo"}}, {"type": "node", "id": 1267855219, "lat": 50.8436468, "lon": 4.4355272, "tags": {"amenity": "bar", "name": "Bistro Op-Weule", "opening_hours": "Tu-Fr 11:00-23:00; Su 11:00-18:00"}}, {"type": "node", "id": 12230103536, "lat": 50.8410768, "lon": 4.4347083, "tags": {"amenity": "bar", "check_date": "2024-07-11", "name": "Zanzibar"}}, {"type": "node", "id": 12230103537, "lat": 50.8411029, "lon": 4.4346467, "tags": {"amenity": "bar", "check_date": "2024-07-11", "name": "Mood", "opening_hours": "We,Th 19:00-02:00, Fr 19:00-03:00, Sa 21:00-03:00"}}]}